noderoom/__init__.py
noderoom/__main__.py
noderoom/formatting.py
noderoom/nodescript_parser.py
noderoom-0.9.3.dist-info/licenses/LICENSE
noderoom-0.9.3.dist-info/METADATA
noderoom-0.9.3.dist-info/WHEEL
noderoom-0.9.3.dist-info/top_level.txt
noderoom-0.9.3.dist-info/RECORD
