Metadata-Version: 2.4
Name: noderoom
Version: 0.9.3
Summary: A collaborative chatroom framework for local AI experiments
Author: Henry Jones
License: MIT
License-File: LICENSE
Requires-Dist: requests>=2.31
Dynamic: license-file
